bili_ticket_gt_python-0.3.2.dist-info/METADATA
bili_ticket_gt_python-0.3.2.dist-info/WHEEL
bili_ticket_gt_python-0.3.2.dist-info/licenses/LICENSE
bili_ticket_gt_python/bili_ticket_gt_python.pyi
bili_ticket_gt_python/__init__.py
bili_ticket_gt_python/bili_ticket_gt_python.cp312-win_amd64.pyd
bili_ticket_gt_python-0.3.2.dist-info/RECORD
